drawler/__init__.py
drawler/_const.py
drawler/comment.py
drawler/core.py
drawler/list.py
drawler/post.py
jar/KotlinInside-1.10.2-all.jar
jar/__init__.py
drawler-0.0.11.dist-info/LICENSE
drawler-0.0.11.dist-info/METADATA
drawler-0.0.11.dist-info/WHEEL
drawler-0.0.11.dist-info/top_level.txt
drawler-0.0.11.dist-info/RECORD
