Metadata-Version: 2.1
Name: drawler
Version: 0.0.11
License: Copyright (c) 2018 The Python Packaging Authority        
Classifier: Programming Language :: Python :: 3
Classifier: License :: OSI Approved :: MIT License
Classifier: Operating System :: OS Independent
Requires-Python: >=3.7
License-File: LICENSE
Requires-Dist: requests
Requires-Dist: numpy
Requires-Dist: jnius
